postal/__init__.py
postal/cli.py
postal/commands/__init__.py
postal/commands/call.py
postal/commands/compose.py
postal/commands/config.py
postal/commands/deploy.py
postal/commands/enter.py
postal/commands/launch.py
postal/commands/login.py
postal/commands/swarm.py
postal/commands/version.py
postal/core/__init__.py
postal/core/config.py
postal/core/db.py
postal/core/rpc.py
postal/core/settings.py
postal/core/swarm.py
postal/core/utils.py
docker_postal-0.0.13.dist-info/entry_points.txt
docker_postal-0.0.13.dist-info/LICENSE
docker_postal-0.0.13.dist-info/WHEEL
docker_postal-0.0.13.dist-info/METADATA
docker_postal-0.0.13.dist-info/RECORD
