Metadata-Version: 2.1
Name: docker-postal
Version: 0.0.13
Summary: A light Docker control tool designed around compose and swarm
Home-page: https://github.com/leviat-tech/postal
License: MIT
Author: Stephen
Requires-Python: >=3.6,<4.0
Classifier: License :: OSI Approved :: MIT License
Classifier: Operating System :: OS Independent
Classifier: Programming Language :: Python :: 3
Classifier: Programming Language :: Python :: 3.6
Classifier: Programming Language :: Python :: 3.7
Classifier: Programming Language :: Python :: 3.8
Classifier: Programming Language :: Python :: 3.9
Requires-Dist: appdirs (>=1.4.4,<2.0.0)
Requires-Dist: boto (>=2.49.0,<3.0.0)
Requires-Dist: importlib-metadata (>=3.7.3,<4.0.0)
Project-URL: Repository, https://github.com/leviat-tech/postal
